<?xml version="1.0" encoding="utf-8"?>
<location id="BRI">
   <name>Brig</name>
   <games>
      <game id="SWI">
         <title>Switzerland</title>
      </game>
   </games>
   <connections>
      <location id="SIO"
                length="3"
                tunnel="true"
                ferry="0"
                microlight="false">
         <name>Sion</name>
         <colour>Black</colour>
      </location>
      <location id="ITA1"
                length="3"
                tunnel="true"
                ferry="0"
                microlight="false">
         <name>Italia (ITA1)</name>
         <colour>Green</colour>
      </location>
      <location id="LOC"
                length="6"
                tunnel="true"
                ferry="0"
                microlight="false">
         <name>Locarno</name>
         <colour>Grey</colour>
      </location>
      <location id="WAS"
                length="4"
                tunnel="true"
                ferry="0"
                microlight="false">
         <name>Wassen</name>
         <colour>Red</colour>
      </location>
      <location id="INT"
                length="2"
                tunnel="true"
                ferry="0"
                microlight="false">
         <name>Interlaken</name>
         <colour>White</colour>
      </location>
   </connections>
   <shortest-paths>
      <location id="GEN" distance="13">
         <name>Geneve</name>
      </location>
      <location id="LAU" distance="9">
         <name>Lausanne</name>
      </location>
      <location id="MAR" distance="5">
         <name>Martigny</name>
      </location>
      <location id="SIO" distance="3">
         <name>Sion</name>
      </location>
      <location id="LOC" distance="6">
         <name>Locarno</name>
      </location>
      <location id="WAS" distance="4">
         <name>Wassen</name>
      </location>
      <location id="INT" distance="2">
         <name>Interlaken</name>
      </location>
      <location id="FRI" distance="6">
         <name>Fribourg</name>
      </location>
      <location id="YVE" distance="9">
         <name>Yverdon</name>
      </location>
      <location id="LUG" distance="7">
         <name>Lugano</name>
      </location>
      <location id="BEL" distance="7">
         <name>Bellinzona</name>
      </location>
      <location id="CDF" distance="8">
         <name>La Chaux-de-fonds</name>
      </location>
      <location id="NEU" distance="7">
         <name sort="Neuchatel">Neuchâtel</name>
      </location>
      <location id="BER" distance="5">
         <name>Bern</name>
      </location>
      <location id="DEL" distance="8">
         <name sort="Delemont">Delémont</name>
      </location>
      <location id="BAS" distance="10">
         <name>Basel</name>
      </location>
      <location id="SOL" distance="7">
         <name>Solothurn</name>
      </location>
      <location id="BAD" distance="9">
         <name>Baden</name>
      </location>
      <location id="OLT" distance="8">
         <name>Olten</name>
      </location>
      <location id="LUZ" distance="6">
         <name>Luzern</name>
      </location>
      <location id="ZUG" distance="7">
         <name>Zug</name>
      </location>
      <location id="SWZ" distance="6">
         <name>Schwyz</name>
      </location>
      <location id="PFA" distance="7">
         <name sort="Pfaffikon">Pfäffikon</name>
      </location>
      <location id="ZUR" distance="8">
         <name sort="Zurich">Zürich</name>
      </location>
      <location id="SFH" distance="10">
         <name>Schaffhausen</name>
      </location>
      <location id="WIN" distance="9">
         <name>Winterthur</name>
      </location>
      <location id="STG" distance="10">
         <name>St Gallen</name>
      </location>
      <location id="VAD" distance="11">
         <name>Vaduz</name>
      </location>
      <location id="KRE" distance="11">
         <name>Kreuzlingen</name>
      </location>
      <location id="SAR" distance="10">
         <name>Sargans</name>
      </location>
      <location id="CHU" distance="9">
         <name>Chur</name>
      </location>
      <location id="DAV" distance="11">
         <name>Davos</name>
      </location>
      <location id="BRU" distance="14">
         <name>Brusio</name>
      </location>
      <location id="FRA1" distance="10">
         <name>France (FRA1)</name>
      </location>
      <location id="FRA2" distance="10">
         <name>France (FRA2)</name>
      </location>
      <location id="FRA3" distance="14">
         <name>France (FRA3)</name>
      </location>
      <location id="FRA4" distance="7">
         <name>France (FRA4)</name>
      </location>
      <location id="ITA1" distance="3">
         <name>Italia (ITA1)</name>
      </location>
      <location id="ITA2" distance="8">
         <name>Italia (ITA2)</name>
      </location>
      <location id="ITA3" distance="9">
         <name>Italia (ITA3)</name>
      </location>
      <location id="ITA4" distance="16">
         <name>Italia (ITA4)</name>
      </location>
      <location id="ITA5" distance="14">
         <name>Italia (ITA5)</name>
      </location>
      <location id="GER1" distance="11">
         <name>Deutschland (GER1)</name>
      </location>
      <location id="GER2" distance="11">
         <name>Deutschland (GER2)</name>
      </location>
      <location id="GER3" distance="12">
         <name>Deutschland (GER3)</name>
      </location>
      <location id="GER4" distance="12">
         <name>Deutschland (GER4)</name>
      </location>
      <location id="GER5" distance="12">
         <name>Deutschland (GER5)</name>
      </location>
      <location id="AUS1" distance="14">
         <name sort="Osterreich (AUS1)">Österreich (AUS1)</name>
      </location>
      <location id="AUS2" distance="12">
         <name sort="Osterreich (AUS2)">Österreich (AUS2)</name>
      </location>
      <location id="AUS3" distance="14">
         <name sort="Osterreich (AUS3)">Österreich (AUS3)</name>
      </location>
   </shortest-paths>
</location>
